user/src/Library/mem_block.v
module mem_block #(
    parameter SIZE   = 8,
    parameter ADDR_WIDTH = 32,
    parameter DATA_WIDTH = 64
)(
    input                                               clk_i,
    input  [$clog2(DATA_WIDTH/SIZE):0]                  write_bits_i,
    input  [ADDR_WIDTH-1:0]                             addr_i,
    input  [DATA_WIDTH-1:0]                             data_i,
    output [DATA_WIDTH-1:0]                             data_o
);
    
    // 
    generate
        genvar i;
        if(ADDR_WIDTH<=16) begin: less_and_equal_16
            reg [SIZE-1:0] block [2**ADDR_WIDTH-1:0];
            for(i=0; i<DATA_WIDTH / SIZE ; i = i + 1 ) begin
                assign data_o[i * 8 +: 8]  = block[addr_i + i];
            end
            integer x;
            /* verilator lint_off WIDTHEXPAND */
            /* verilator lint_off BLKSEQ */
            always @(posedge clk_i) begin
                for (x = 0; x < write_bits_i ; x = x + 1) begin 
                    block[addr_i + x] =  data_i[x * 8 +: 8];
                end
            end
            /* verilator lint_on BLKSEQ */
            /* verilator lint_on WIDTHEXPAND */
        end else begin: more_16
            for(i= 0; i < (2**(ADDR_WIDTH-16)); i=i+1) begin: mem_block
                reg [SIZE-1:0] block [2**16-1:0];
            end
            for(i=0; i<DATA_WIDTH / SIZE ; i = i + 1 ) begin
                assign data_o[i * 8 +: 8]  = mem_block[addr_i[ADDR_WIDTH-1:16]].block[addr_i[15:0] + i];
            end
            integer x;
            /* verilator lint_off WIDTHEXPAND */
            /* verilator lint_off BLKSEQ */
            always @(posedge clk_i) begin
                for (x = 0; x < write_bits_i ; x = x + 1) begin 
                    mem_block[addr_i[ADDR_WIDTH-1:16]].block[addr_i[15:0] + x] =  data_i[x * 8 +: 8];
                end
            end
            /* verilator lint_on BLKSEQ */
            /* verilator lint_on WIDTHEXPAND */
        end
    endgenerate

endmodule //mem_block

user/src/Library/waveform.vcd
$version Generated by VerilatedVcd $end
$timescale 1ps $end

 $scope module TOP $end
  $var wire 16 % addr_i [15:0] $end
  $var wire  1 # clk_i $end
  $var wire 64 & data_i [63:0] $end
  $var wire 64 ( data_o [63:0] $end
  $var wire  4 $ write_bits_i [3:0] $end
  $scope module mem_block $end
   $var wire 32 , ADDR_WIDTH [31:0] $end
   $var wire 32 - DATA_WIDTH [31:0] $end
   $var wire 32 + SIZE [31:0] $end
   $var wire 16 % addr_i [15:0] $end
   $var wire  1 # clk_i $end
   $var wire 64 & data_i [63:0] $end
   $var wire 64 ( data_o [63:0] $end
   $var wire  4 $ write_bits_i [3:0] $end
   $scope module less_and_equal_16 $end
    $var wire 32 * x [31:0] $end
   $upscope $end
  $upscope $end
 $upscope $end
$enddefinitions $end


#0
0#
b1000 $
b0000000000000100 %
b1111111111111111111111111111111111111111111111111111111111110011 &
b0000000000000000000000000000000000000000000000000000000000000000 (
b00000000000000000000000000000000 *
b00000000000000000000000000001000 +
b00000000000000000000000000010000 ,
b00000000000000000000000001000000 -
#1
1#
b0000000000001000 %
b1111111111111111111111111111111111111111111111111111111111110110 &
b1111111111111111111111111111111111111111111111111111111111110110 (
b00000000000000000000000000001000 *
#2
0#
b0000000000001100 %
b1111111111111111111111111111111111111111111111111111111111111001 &
b0000000000000000000000000000000011111111111111111111111111111111 (
#3
1#
b0000000000010000 %
b1111111111111111111111111111111111111111111111111111111111111100 &
b1111111111111111111111111111111111111111111111111111111111111100 (
#4
0#
b0000000000010100 %
b1111111111111111111111111111111111111111111111111111111111111111 &
b0000000000000000000000000000000011111111111111111111111111111111 (
#5
1#
b0000000000011000 %
b0000000000000000000000000000000000000000000000000000000000000010 &
b0000000000000000000000000000000000000000000000000000000000000010 (
#6
0#
b0000000000011100 %
b0000000000000000000000000000000000000000000000000000000000000101 &
b0000000000000000000000000000000000000000000000000000000000000000 (
#7
1#
b0000000000100000 %
b0000000000000000000000000000000000000000000000000000000000001000 &
b0000000000000000000000000000000000000000000000000000000000001000 (
#8
0#
b0000000000100100 %
b0000000000000000000000000000000000000000000000000000000000001011 &
b0000000000000000000000000000000000000000000000000000000000000000 (
#9
1#
b0000000000101000 %
b0000000000000000000000000000000000000000000000000000000000001110 &
b0000000000000000000000000000000000000000000000000000000000001110 (
#10
0#
b0000000000101100 %
b0000000000000000000000000000000000000000000000000000000000010001 &
b0000000000000000000000000000000000000000000000000000000000000000 (
#11
1#
b0000000000110000 %
b0000000000000000000000000000000000000000000000000000000000010100 &
b0000000000000000000000000000000000000000000000000000000000010100 (
#12
0#
b0000000000110100 %
b0000000000000000000000000000000000000000000000000000000000010111 &
b0000000000000000000000000000000000000000000000000000000000000000 (
#13
1#
b0000000000111000 %
b0000000000000000000000000000000000000000000000000000000000011010 &
b0000000000000000000000000000000000000000000000000000000000011010 (
#14
0#
b0000000000111100 %
b0000000000000000000000000000000000000000000000000000000000011101 &
b0000000000000000000000000000000000000000000000000000000000000000 (
#15
1#
b0000000001000000 %
b0000000000000000000000000000000000000000000000000000000000100000 &
b0000000000000000000000000000000000000000000000000000000000100000 (
#16
0#
b0000000001000100 %
b0000000000000000000000000000000000000000000000000000000000100011 &
b0000000000000000000000000000000000000000000000000000000000000000 (
#17
1#
b0000000001001000 %
b0000000000000000000000000000000000000000000000000000000000100110 &
b0000000000000000000000000000000000000000000000000000000000100110 (
#18
0#
b0000000001001100 %
b0000000000000000000000000000000000000000000000000000000000101001 &
b0000000000000000000000000000000000000000000000000000000000000000 (
#19
1#
b0000000001010000 %
b0000000000000000000000000000000000000000000000000000000000101100 &
b0000000000000000000000000000000000000000000000000000000000101100 (
#20
0#
b0000000001010100 %
b0000000000000000000000000000000000000000000000000000000000101111 &
b0000000000000000000000000000000000000000000000000000000000000000 (
#21
1#
b0000000001011000 %
b0000000000000000000000000000000000000000000000000000000000110010 &
b0000000000000000000000000000000000000000000000000000000000110010 (
#22
0#
b0000000001011100 %
b0000000000000000000000000000000000000000000000000000000000110101 &
b0000000000000000000000000000000000000000000000000000000000000000 (
#23
1#
b0000000001100000 %
b0000000000000000000000000000000000000000000000000000000000111000 &
b0000000000000000000000000000000000000000000000000000000000111000 (
#24
0#
b0000000001100100 %
b0000000000000000000000000000000000000000000000000000000000111011 &
b0000000000000000000000000000000000000000000000000000000000000000 (
#25
1#
b0000000001101000 %
b0000000000000000000000000000000000000000000000000000000000111110 &
b0000000000000000000000000000000000000000000000000000000000111110 (
#26
0#
b0000000001101100 %
b0000000000000000000000000000000000000000000000000000000001000001 &
b0000000000000000000000000000000000000000000000000000000000000000 (
#27
1#
b0000000001110000 %
b0000000000000000000000000000000000000000000000000000000001000100 &
b0000000000000000000000000000000000000000000000000000000001000100 (
#28
0#
b0000000001110100 %
b0000000000000000000000000000000000000000000000000000000001000111 &
b0000000000000000000000000000000000000000000000000000000000000000 (
#29
1#
b0000000001111000 %
b0000000000000000000000000000000000000000000000000000000001001010 &
b0000000000000000000000000000000000000000000000000000000001001010 (
#30
0#
b0000000001111100 %
b0000000000000000000000000000000000000000000000000000000001001101 &
b0000000000000000000000000000000000000000000000000000000000000000 (
#31
1#
b0000000010000000 %
b0000000000000000000000000000000000000000000000000000000001010000 &
b0000000000000000000000000000000000000000000000000000000001010000 (
#32
0#
b0000000010000100 %
b0000000000000000000000000000000000000000000000000000000001010011 &
b0000000000000000000000000000000000000000000000000000000000000000 (
#33
1#
b0000000010001000 %
b0000000000000000000000000000000000000000000000000000000001010110 &
b0000000000000000000000000000000000000000000000000000000001010110 (
#34
0#
b0000000010001100 %
b0000000000000000000000000000000000000000000000000000000001011001 &
b0000000000000000000000000000000000000000000000000000000000000000 (
#35
1#
b0000000010010000 %
b0000000000000000000000000000000000000000000000000000000001011100 &
b0000000000000000000000000000000000000000000000000000000001011100 (
#36
0#
b0000000010010100 %
b0000000000000000000000000000000000000000000000000000000001011111 &
b0000000000000000000000000000000000000000000000000000000000000000 (
#37
1#
b0000000010011000 %
b0000000000000000000000000000000000000000000000000000000001100010 &
b0000000000000000000000000000000000000000000000000000000001100010 (
#38
0#
b0000000010011100 %
b0000000000000000000000000000000000000000000000000000000001100101 &
b0000000000000000000000000000000000000000000000000000000000000000 (
#39
1#
b0000000010100000 %
b0000000000000000000000000000000000000000000000000000000001101000 &
b0000000000000000000000000000000000000000000000000000000001101000 (
#40
0#
b0000000010100100 %
b0000000000000000000000000000000000000000000000000000000001101011 &
b0000000000000000000000000000000000000000000000000000000000000000 (
#41
1#
b0000000010101000 %
b0000000000000000000000000000000000000000000000000000000001101110 &
b0000000000000000000000000000000000000000000000000000000001101110 (
#42
0#
b0000000010101100 %
b0000000000000000000000000000000000000000000000000000000001110001 &
b0000000000000000000000000000000000000000000000000000000000000000 (
#43
1#
b0000000010110000 %
b0000000000000000000000000000000000000000000000000000000001110100 &
b0000000000000000000000000000000000000000000000000000000001110100 (
#44
0#
b0000000010110100 %
b0000000000000000000000000000000000000000000000000000000001110111 &
b0000000000000000000000000000000000000000000000000000000000000000 (
#45
1#
b0000000010111000 %
b0000000000000000000000000000000000000000000000000000000001111010 &
b0000000000000000000000000000000000000000000000000000000001111010 (
#46
0#
b0000000010111100 %
b0000000000000000000000000000000000000000000000000000000001111101 &
b0000000000000000000000000000000000000000000000000000000000000000 (
#47
1#
b0000000011000000 %
b0000000000000000000000000000000000000000000000000000000010000000 &
b0000000000000000000000000000000000000000000000000000000010000000 (
#48
0#
b0000000011000100 %
b0000000000000000000000000000000000000000000000000000000010000011 &
b0000000000000000000000000000000000000000000000000000000000000000 (
#49
1#
b0000000011001000 %
b0000000000000000000000000000000000000000000000000000000010000110 &
b0000000000000000000000000000000000000000000000000000000010000110 (
#50
0#
b0000000011001100 %
b0000000000000000000000000000000000000000000000000000000010001001 &
b0000000000000000000000000000000000000000000000000000000000000000 (
#51
1#
b0000000011010000 %
b0000000000000000000000000000000000000000000000000000000010001100 &
b0000000000000000000000000000000000000000000000000000000010001100 (
#52
0#
b0000000011010100 %
b0000000000000000000000000000000000000000000000000000000010001111 &
b0000000000000000000000000000000000000000000000000000000000000000 (
#53
1#
b0000000011011000 %
b0000000000000000000000000000000000000000000000000000000010010010 &
b0000000000000000000000000000000000000000000000000000000010010010 (
#54
0#
b0000000011011100 %
b0000000000000000000000000000000000000000000000000000000010010101 &
b0000000000000000000000000000000000000000000000000000000000000000 (
#55
1#
b0000000011100000 %
b0000000000000000000000000000000000000000000000000000000010011000 &
b0000000000000000000000000000000000000000000000000000000010011000 (
#56
0#
b0000000011100100 %
b0000000000000000000000000000000000000000000000000000000010011011 &
b0000000000000000000000000000000000000000000000000000000000000000 (
#57
1#
b0000000011101000 %
b0000000000000000000000000000000000000000000000000000000010011110 &
b0000000000000000000000000000000000000000000000000000000010011110 (
#58
0#
b0000000011101100 %
b0000000000000000000000000000000000000000000000000000000010100001 &
b0000000000000000000000000000000000000000000000000000000000000000 (
#59
1#
b0000000011110000 %
b0000000000000000000000000000000000000000000000000000000010100100 &
b0000000000000000000000000000000000000000000000000000000010100100 (
#60
0#
b0000000011110100 %
b0000000000000000000000000000000000000000000000000000000010100111 &
b0000000000000000000000000000000000000000000000000000000000000000 (
#61
1#
b0000000011111000 %
b0000000000000000000000000000000000000000000000000000000010101010 &
b0000000000000000000000000000000000000000000000000000000010101010 (
#62
0#
b0000000011111100 %
b0000000000000000000000000000000000000000000000000000000010101101 &
b0000000000000000000000000000000000000000000000000000000000000000 (
#63
1#
b0000000100000000 %
b0000000000000000000000000000000000000000000000000000000010110000 &
b0000000000000000000000000000000000000000000000000000000010110000 (
#64
0#
b0000000100000100 %
b0000000000000000000000000000000000000000000000000000000010110011 &
b0000000000000000000000000000000000000000000000000000000000000000 (
#65
1#
b0000000100001000 %
b0000000000000000000000000000000000000000000000000000000010110110 &
b0000000000000000000000000000000000000000000000000000000010110110 (
#66
0#
b0000000100001100 %
b0000000000000000000000000000000000000000000000000000000010111001 &
b0000000000000000000000000000000000000000000000000000000000000000 (
#67
1#
b0000000100010000 %
b0000000000000000000000000000000000000000000000000000000010111100 &
b0000000000000000000000000000000000000000000000000000000010111100 (
#68
0#
b0000000100010100 %
b0000000000000000000000000000000000000000000000000000000010111111 &
b0000000000000000000000000000000000000000000000000000000000000000 (
#69
1#
b0000000100011000 %
b0000000000000000000000000000000000000000000000000000000011000010 &
b0000000000000000000000000000000000000000000000000000000011000010 (
#70
0#
b0000000100011100 %
b0000000000000000000000000000000000000000000000000000000011000101 &
b0000000000000000000000000000000000000000000000000000000000000000 (
#71
1#
b0000000100100000 %
b0000000000000000000000000000000000000000000000000000000011001000 &
b0000000000000000000000000000000000000000000000000000000011001000 (
#72
0#
b0000000100100100 %
b0000000000000000000000000000000000000000000000000000000011001011 &
b0000000000000000000000000000000000000000000000000000000000000000 (
#73
1#
b0000000100101000 %
b0000000000000000000000000000000000000000000000000000000011001110 &
b0000000000000000000000000000000000000000000000000000000011001110 (
#74
0#
b0000000100101100 %
b0000000000000000000000000000000000000000000000000000000011010001 &
b0000000000000000000000000000000000000000000000000000000000000000 (
#75
1#
b0000000100110000 %
b0000000000000000000000000000000000000000000000000000000011010100 &
b0000000000000000000000000000000000000000000000000000000011010100 (
#76
0#
b0000000100110100 %
b0000000000000000000000000000000000000000000000000000000011010111 &
b0000000000000000000000000000000000000000000000000000000000000000 (
#77
1#
b0000000100111000 %
b0000000000000000000000000000000000000000000000000000000011011010 &
b0000000000000000000000000000000000000000000000000000000011011010 (
#78
0#
b0000000100111100 %
b0000000000000000000000000000000000000000000000000000000011011101 &
b0000000000000000000000000000000000000000000000000000000000000000 (
#79
1#
b0000000101000000 %
b0000000000000000000000000000000000000000000000000000000011100000 &
b0000000000000000000000000000000000000000000000000000000011100000 (
#80
0#
b0000000101000100 %
b0000000000000000000000000000000000000000000000000000000011100011 &
b0000000000000000000000000000000000000000000000000000000000000000 (
#81
1#
b0000000101001000 %
b0000000000000000000000000000000000000000000000000000000011100110 &
b0000000000000000000000000000000000000000000000000000000011100110 (
#82
0#
b0000000101001100 %
b0000000000000000000000000000000000000000000000000000000011101001 &
b0000000000000000000000000000000000000000000000000000000000000000 (
#83
1#
b0000000101010000 %
b0000000000000000000000000000000000000000000000000000000011101100 &
b0000000000000000000000000000000000000000000000000000000011101100 (
#84
0#
b0000000101010100 %
b0000000000000000000000000000000000000000000000000000000011101111 &
b0000000000000000000000000000000000000000000000000000000000000000 (
#85
1#
b0000000101011000 %
b0000000000000000000000000000000000000000000000000000000011110010 &
b0000000000000000000000000000000000000000000000000000000011110010 (
#86
0#
b0000000101011100 %
b0000000000000000000000000000000000000000000000000000000011110101 &
b0000000000000000000000000000000000000000000000000000000000000000 (
#87
1#
b0000000101100000 %
b0000000000000000000000000000000000000000000000000000000011111000 &
b0000000000000000000000000000000000000000000000000000000011111000 (
#88
0#
b0000000101100100 %
b0000000000000000000000000000000000000000000000000000000011111011 &
b0000000000000000000000000000000000000000000000000000000000000000 (
#89
1#
b0000000101101000 %
b0000000000000000000000000000000000000000000000000000000011111110 &
b0000000000000000000000000000000000000000000000000000000011111110 (
#90
0#
b0000000101101100 %
b0000000000000000000000000000000000000000000000000000000100000001 &
b0000000000000000000000000000000000000000000000000000000000000000 (
#91
1#
b0000000101110000 %
b0000000000000000000000000000000000000000000000000000000100000100 &
b0000000000000000000000000000000000000000000000000000000100000100 (
#92
0#
b0000000101110100 %
b0000000000000000000000000000000000000000000000000000000100000111 &
b0000000000000000000000000000000000000000000000000000000000000000 (
#93
1#
b0000000101111000 %
b0000000000000000000000000000000000000000000000000000000100001010 &
b0000000000000000000000000000000000000000000000000000000100001010 (
#94
0#
b0000000101111100 %
b0000000000000000000000000000000000000000000000000000000100001101 &
b0000000000000000000000000000000000000000000000000000000000000000 (
#95
1#
b0000000110000000 %
b0000000000000000000000000000000000000000000000000000000100010000 &
b0000000000000000000000000000000000000000000000000000000100010000 (
#96
0#
b0000000110000100 %
b0000000000000000000000000000000000000000000000000000000100010011 &
b0000000000000000000000000000000000000000000000000000000000000000 (
#97
1#
b0000000110001000 %
b0000000000000000000000000000000000000000000000000000000100010110 &
b0000000000000000000000000000000000000000000000000000000100010110 (
#98
0#
b0000000110001100 %
b0000000000000000000000000000000000000000000000000000000100011001 &
b0000000000000000000000000000000000000000000000000000000000000000 (
#99
1#
b0000000110010000 %
b0000000000000000000000000000000000000000000000000000000100011100 &
b0000000000000000000000000000000000000000000000000000000100011100 (
#100
0#
b0000000110010100 %
b0000000000000000000000000000000000000000000000000000000100011111 &
b0000000000000000000000000000000000000000000000000000000000000000 (
#101
1#
b0000 $
b0000000000000000 %
b1111111111111111111111111111111111111111111111111111111111110000 &
b00000000000000000000000000000000 *
#102
0#
b0000000000000100 %
b1111111111111111111111111111111111111111111111111111111111110011 &
b1111111111111111111111111111011000000000000000000000000000000000 (
#103
1#
b0000000000001000 %
b1111111111111111111111111111111111111111111111111111111111110110 &
b1111111111111111111111111111111111111111111111111111111111110110 (
#104
0#
b0000000000001100 %
b1111111111111111111111111111111111111111111111111111111111111001 &
b1111111111111111111111111111110011111111111111111111111111111111 (
#105
1#
b0000000000010000 %
b1111111111111111111111111111111111111111111111111111111111111100 &
b1111111111111111111111111111111111111111111111111111111111111100 (
#106
0#
b0000000000010100 %
b1111111111111111111111111111111111111111111111111111111111111111 &
b0000000000000000000000000000001011111111111111111111111111111111 (
#107
1#
b0000000000011000 %
b0000000000000000000000000000000000000000000000000000000000000010 &
b0000000000000000000000000000000000000000000000000000000000000010 (
#108
0#
b0000000000011100 %
b0000000000000000000000000000000000000000000000000000000000000101 &
b0000000000000000000000000000100000000000000000000000000000000000 (
#109
1#
b0000000000100000 %
b0000000000000000000000000000000000000000000000000000000000001000 &
b0000000000000000000000000000000000000000000000000000000000001000 (
#110
0#
b0000000000100100 %
b0000000000000000000000000000000000000000000000000000000000001011 &
b0000000000000000000000000000111000000000000000000000000000000000 (
#111
1#
b0000000000101000 %
b0000000000000000000000000000000000000000000000000000000000001110 &
b0000000000000000000000000000000000000000000000000000000000001110 (
#112
0#
b0000000000101100 %
b0000000000000000000000000000000000000000000000000000000000010001 &
b0000000000000000000000000001010000000000000000000000000000000000 (
#113
1#
b0000000000110000 %
b0000000000000000000000000000000000000000000000000000000000010100 &
b0000000000000000000000000000000000000000000000000000000000010100 (
#114
0#
b0000000000110100 %
b0000000000000000000000000000000000000000000000000000000000010111 &
b0000000000000000000000000001101000000000000000000000000000000000 (
#115
1#
b0000000000111000 %
b0000000000000000000000000000000000000000000000000000000000011010 &
b0000000000000000000000000000000000000000000000000000000000011010 (
#116
0#
b0000000000111100 %
b0000000000000000000000000000000000000000000000000000000000011101 &
b0000000000000000000000000010000000000000000000000000000000000000 (
#117
1#
b0000000001000000 %
b0000000000000000000000000000000000000000000000000000000000100000 &
b0000000000000000000000000000000000000000000000000000000000100000 (
#118
0#
b0000000001000100 %
b0000000000000000000000000000000000000000000000000000000000100011 &
b0000000000000000000000000010011000000000000000000000000000000000 (
#119
1#
b0000000001001000 %
b0000000000000000000000000000000000000000000000000000000000100110 &
b0000000000000000000000000000000000000000000000000000000000100110 (
#120
0#
b0000000001001100 %
b0000000000000000000000000000000000000000000000000000000000101001 &
b0000000000000000000000000010110000000000000000000000000000000000 (
#121
1#
b0000000001010000 %
b0000000000000000000000000000000000000000000000000000000000101100 &
b0000000000000000000000000000000000000000000000000000000000101100 (
#122
0#
b0000000001010100 %
b0000000000000000000000000000000000000000000000000000000000101111 &
b0000000000000000000000000011001000000000000000000000000000000000 (
#123
1#
b0000000001011000 %
b0000000000000000000000000000000000000000000000000000000000110010 &
b0000000000000000000000000000000000000000000000000000000000110010 (
#124
0#
b0000000001011100 %
b0000000000000000000000000000000000000000000000000000000000110101 &
b0000000000000000000000000011100000000000000000000000000000000000 (
#125
1#
b0000000001100000 %
b0000000000000000000000000000000000000000000000000000000000111000 &
b0000000000000000000000000000000000000000000000000000000000111000 (
#126
0#
b0000000001100100 %
b0000000000000000000000000000000000000000000000000000000000111011 &
b0000000000000000000000000011111000000000000000000000000000000000 (
#127
1#
b0000000001101000 %
b0000000000000000000000000000000000000000000000000000000000111110 &
b0000000000000000000000000000000000000000000000000000000000111110 (
#128
0#
b0000000001101100 %
b0000000000000000000000000000000000000000000000000000000001000001 &
b0000000000000000000000000100010000000000000000000000000000000000 (
#129
1#
b0000000001110000 %
b0000000000000000000000000000000000000000000000000000000001000100 &
b0000000000000000000000000000000000000000000000000000000001000100 (
#130
0#
b0000000001110100 %
b0000000000000000000000000000000000000000000000000000000001000111 &
b0000000000000000000000000100101000000000000000000000000000000000 (
#131
1#
b0000000001111000 %
b0000000000000000000000000000000000000000000000000000000001001010 &
b0000000000000000000000000000000000000000000000000000000001001010 (
#132
0#
b0000000001111100 %
b0000000000000000000000000000000000000000000000000000000001001101 &
b0000000000000000000000000101000000000000000000000000000000000000 (
#133
1#
b0000000010000000 %
b0000000000000000000000000000000000000000000000000000000001010000 &
b0000000000000000000000000000000000000000000000000000000001010000 (
#134
0#
b0000000010000100 %
b0000000000000000000000000000000000000000000000000000000001010011 &
b0000000000000000000000000101011000000000000000000000000000000000 (
#135
1#
b0000000010001000 %
b0000000000000000000000000000000000000000000000000000000001010110 &
b0000000000000000000000000000000000000000000000000000000001010110 (
#136
0#
b0000000010001100 %
b0000000000000000000000000000000000000000000000000000000001011001 &
b0000000000000000000000000101110000000000000000000000000000000000 (
#137
1#
b0000000010010000 %
b0000000000000000000000000000000000000000000000000000000001011100 &
b0000000000000000000000000000000000000000000000000000000001011100 (
#138
0#
b0000000010010100 %
b0000000000000000000000000000000000000000000000000000000001011111 &
b0000000000000000000000000110001000000000000000000000000000000000 (
#139
1#
b0000000010011000 %
b0000000000000000000000000000000000000000000000000000000001100010 &
b0000000000000000000000000000000000000000000000000000000001100010 (
#140
0#
b0000000010011100 %
b0000000000000000000000000000000000000000000000000000000001100101 &
b0000000000000000000000000110100000000000000000000000000000000000 (
#141
1#
b0000000010100000 %
b0000000000000000000000000000000000000000000000000000000001101000 &
b0000000000000000000000000000000000000000000000000000000001101000 (
#142
0#
b0000000010100100 %
b0000000000000000000000000000000000000000000000000000000001101011 &
b0000000000000000000000000110111000000000000000000000000000000000 (
#143
1#
b0000000010101000 %
b0000000000000000000000000000000000000000000000000000000001101110 &
b0000000000000000000000000000000000000000000000000000000001101110 (
#144
0#
b0000000010101100 %
b0000000000000000000000000000000000000000000000000000000001110001 &
b0000000000000000000000000111010000000000000000000000000000000000 (
#145
1#
b0000000010110000 %
b0000000000000000000000000000000000000000000000000000000001110100 &
b0000000000000000000000000000000000000000000000000000000001110100 (
#146
0#
b0000000010110100 %
b0000000000000000000000000000000000000000000000000000000001110111 &
b0000000000000000000000000111101000000000000000000000000000000000 (
#147
1#
b0000000010111000 %
b0000000000000000000000000000000000000000000000000000000001111010 &
b0000000000000000000000000000000000000000000000000000000001111010 (
#148
0#
b0000000010111100 %
b0000000000000000000000000000000000000000000000000000000001111101 &
b0000000000000000000000001000000000000000000000000000000000000000 (
#149
1#
b0000000011000000 %
b0000000000000000000000000000000000000000000000000000000010000000 &
b0000000000000000000000000000000000000000000000000000000010000000 (
#150
0#
b0000000011000100 %
b0000000000000000000000000000000000000000000000000000000010000011 &
b0000000000000000000000001000011000000000000000000000000000000000 (
#151
1#
b0000000011001000 %
b0000000000000000000000000000000000000000000000000000000010000110 &
b0000000000000000000000000000000000000000000000000000000010000110 (
#152
0#
b0000000011001100 %
b0000000000000000000000000000000000000000000000000000000010001001 &
b0000000000000000000000001000110000000000000000000000000000000000 (
#153
1#
b0000000011010000 %
b0000000000000000000000000000000000000000000000000000000010001100 &
b0000000000000000000000000000000000000000000000000000000010001100 (
#154
0#
b0000000011010100 %
b0000000000000000000000000000000000000000000000000000000010001111 &
b0000000000000000000000001001001000000000000000000000000000000000 (
#155
1#
b0000000011011000 %
b0000000000000000000000000000000000000000000000000000000010010010 &
b0000000000000000000000000000000000000000000000000000000010010010 (
#156
0#
b0000000011011100 %
b0000000000000000000000000000000000000000000000000000000010010101 &
b0000000000000000000000001001100000000000000000000000000000000000 (
#157
1#
b0000000011100000 %
b0000000000000000000000000000000000000000000000000000000010011000 &
b0000000000000000000000000000000000000000000000000000000010011000 (
#158
0#
b0000000011100100 %
b0000000000000000000000000000000000000000000000000000000010011011 &
b0000000000000000000000001001111000000000000000000000000000000000 (
#159
1#
b0000000011101000 %
b0000000000000000000000000000000000000000000000000000000010011110 &
b0000000000000000000000000000000000000000000000000000000010011110 (
#160
0#
b0000000011101100 %
b0000000000000000000000000000000000000000000000000000000010100001 &
b0000000000000000000000001010010000000000000000000000000000000000 (
#161
1#
b0000000011110000 %
b0000000000000000000000000000000000000000000000000000000010100100 &
b0000000000000000000000000000000000000000000000000000000010100100 (
#162
0#
b0000000011110100 %
b0000000000000000000000000000000000000000000000000000000010100111 &
b0000000000000000000000001010101000000000000000000000000000000000 (
#163
1#
b0000000011111000 %
b0000000000000000000000000000000000000000000000000000000010101010 &
b0000000000000000000000000000000000000000000000000000000010101010 (
#164
0#
b0000000011111100 %
b0000000000000000000000000000000000000000000000000000000010101101 &
b0000000000000000000000001011000000000000000000000000000000000000 (
#165
1#
b0000000100000000 %
b0000000000000000000000000000000000000000000000000000000010110000 &
b0000000000000000000000000000000000000000000000000000000010110000 (
#166
0#
b0000000100000100 %
b0000000000000000000000000000000000000000000000000000000010110011 &
b0000000000000000000000001011011000000000000000000000000000000000 (
#167
1#
b0000000100001000 %
b0000000000000000000000000000000000000000000000000000000010110110 &
b0000000000000000000000000000000000000000000000000000000010110110 (
#168
0#
b0000000100001100 %
b0000000000000000000000000000000000000000000000000000000010111001 &
b0000000000000000000000001011110000000000000000000000000000000000 (
#169
1#
b0000000100010000 %
b0000000000000000000000000000000000000000000000000000000010111100 &
b0000000000000000000000000000000000000000000000000000000010111100 (
#170
0#
b0000000100010100 %
b0000000000000000000000000000000000000000000000000000000010111111 &
b0000000000000000000000001100001000000000000000000000000000000000 (
#171
1#
b0000000100011000 %
b0000000000000000000000000000000000000000000000000000000011000010 &
b0000000000000000000000000000000000000000000000000000000011000010 (
#172
0#
b0000000100011100 %
b0000000000000000000000000000000000000000000000000000000011000101 &
b0000000000000000000000001100100000000000000000000000000000000000 (
#173
1#
b0000000100100000 %
b0000000000000000000000000000000000000000000000000000000011001000 &
b0000000000000000000000000000000000000000000000000000000011001000 (
#174
0#
b0000000100100100 %
b0000000000000000000000000000000000000000000000000000000011001011 &
b0000000000000000000000001100111000000000000000000000000000000000 (
#175
1#
b0000000100101000 %
b0000000000000000000000000000000000000000000000000000000011001110 &
b0000000000000000000000000000000000000000000000000000000011001110 (
#176
0#
b0000000100101100 %
b0000000000000000000000000000000000000000000000000000000011010001 &
b0000000000000000000000001101010000000000000000000000000000000000 (
#177
1#
b0000000100110000 %
b0000000000000000000000000000000000000000000000000000000011010100 &
b0000000000000000000000000000000000000000000000000000000011010100 (
#178
0#
b0000000100110100 %
b0000000000000000000000000000000000000000000000000000000011010111 &
b0000000000000000000000001101101000000000000000000000000000000000 (
#179
1#
b0000000100111000 %
b0000000000000000000000000000000000000000000000000000000011011010 &
b0000000000000000000000000000000000000000000000000000000011011010 (
#180
0#
b0000000100111100 %
b0000000000000000000000000000000000000000000000000000000011011101 &
b0000000000000000000000001110000000000000000000000000000000000000 (
#181
1#
b0000000101000000 %
b0000000000000000000000000000000000000000000000000000000011100000 &
b0000000000000000000000000000000000000000000000000000000011100000 (
#182
0#
b0000000101000100 %
b0000000000000000000000000000000000000000000000000000000011100011 &
b0000000000000000000000001110011000000000000000000000000000000000 (
#183
1#
b0000000101001000 %
b0000000000000000000000000000000000000000000000000000000011100110 &
b0000000000000000000000000000000000000000000000000000000011100110 (
#184
0#
b0000000101001100 %
b0000000000000000000000000000000000000000000000000000000011101001 &
b0000000000000000000000001110110000000000000000000000000000000000 (
#185
1#
b0000000101010000 %
b0000000000000000000000000000000000000000000000000000000011101100 &
b0000000000000000000000000000000000000000000000000000000011101100 (
#186
0#
b0000000101010100 %
b0000000000000000000000000000000000000000000000000000000011101111 &
b0000000000000000000000001111001000000000000000000000000000000000 (
#187
1#
b0000000101011000 %
b0000000000000000000000000000000000000000000000000000000011110010 &
b0000000000000000000000000000000000000000000000000000000011110010 (
#188
0#
b0000000101011100 %
b0000000000000000000000000000000000000000000000000000000011110101 &
b0000000000000000000000001111100000000000000000000000000000000000 (
#189
1#
b0000000101100000 %
b0000000000000000000000000000000000000000000000000000000011111000 &
b0000000000000000000000000000000000000000000000000000000011111000 (
#190
0#
b0000000101100100 %
b0000000000000000000000000000000000000000000000000000000011111011 &
b0000000000000000000000001111111000000000000000000000000000000000 (
#191
1#
b0000000101101000 %
b0000000000000000000000000000000000000000000000000000000011111110 &
b0000000000000000000000000000000000000000000000000000000011111110 (
#192
0#
b0000000101101100 %
b0000000000000000000000000000000000000000000000000000000100000001 &
b0000000000000000000000010000010000000000000000000000000000000000 (
#193
1#
b0000000101110000 %
b0000000000000000000000000000000000000000000000000000000100000100 &
b0000000000000000000000000000000000000000000000000000000100000100 (
#194
0#
b0000000101110100 %
b0000000000000000000000000000000000000000000000000000000100000111 &
b0000000000000000000000010000101000000000000000000000000000000000 (
#195
1#
b0000000101111000 %
b0000000000000000000000000000000000000000000000000000000100001010 &
b0000000000000000000000000000000000000000000000000000000100001010 (
#196
0#
b0000000101111100 %
b0000000000000000000000000000000000000000000000000000000100001101 &
b0000000000000000000000010001000000000000000000000000000000000000 (
#197
1#
b0000000110000000 %
b0000000000000000000000000000000000000000000000000000000100010000 &
b0000000000000000000000000000000000000000000000000000000100010000 (
#198
0#
b0000000110000100 %
b0000000000000000000000000000000000000000000000000000000100010011 &
b0000000000000000000000010001011000000000000000000000000000000000 (
#199
1#
b0000000110001000 %
b0000000000000000000000000000000000000000000000000000000100010110 &
b0000000000000000000000000000000000000000000000000000000100010110 (
